Changelog
LICENSE
MANIFEST.in
README.md
pyproject.toml
setup.py
docs/Makefile
docs/api-objects.txt
docs/api.rst
docs/class-tree.html
docs/conf.py
docs/crarr.png
docs/help.html
docs/identifier-index.html
docs/index.html
docs/index.rst
docs/installing.rst
docs/make.bat
docs/module-tree.html
docs/_build/doctrees/api.doctree
docs/_build/doctrees/environment.pickle
docs/_build/doctrees/index.doctree
docs/_build/doctrees/installing.doctree
docs/_build/html/.buildinfo
docs/_build/html/api.html
docs/_build/html/genindex.html
docs/_build/html/index.html
docs/_build/html/installing.html
docs/_build/html/objects.inv
docs/_build/html/py-modindex.html
docs/_build/html/search.html
docs/_build/html/searchindex.js
docs/_build/html/_sources/api.rst.txt
docs/_build/html/_sources/index.rst.txt
docs/_build/html/_sources/installing.rst.txt
docs/_build/html/_static/basic.css
docs/_build/html/_static/doctools.js
docs/_build/html/_static/documentation_options.js
docs/_build/html/_static/file.png
docs/_build/html/_static/jquery.js
docs/_build/html/_static/language_data.js
docs/_build/html/_static/minus.png
docs/_build/html/_static/nature.css
docs/_build/html/_static/plus.png
docs/_build/html/_static/pygments.css
docs/_build/html/_static/searchtools.js
docs/_build/html/_static/underscore-1.3.1.js
docs/_build/html/_static/underscore.js
docs/_static/.gitkeep
docs/_static/css/nature2.css
man/cnvgrib1to2.1
man/cnvgrib2to1.1
man/grib_list.1
man/grib_repack.1
sampledata/CMC_reg_WIND_ISBL_300_ps60km_2010052400_P012.grib
sampledata/cl00010000_ecoclimap_rot.grib1
sampledata/ds.maxt.bin
sampledata/ds.waveh.bin
sampledata/dspr.temp.bin
sampledata/ecmwf_tigge.grb
sampledata/eta.grb
sampledata/flux.grb
sampledata/gfs.grb
sampledata/gfs.t12z.pgrbf120.2p5deg.grib2
sampledata/ngm.grb
sampledata/no-radius-shapeOfEarth-7.grb2
sampledata/rap.wrfnat.grib2
sampledata/reduced_latlon_surface.grib2
sampledata/regular_latlon_surface.grib1
sampledata/regular_latlon_surface.grib2
sampledata/rotated_ll.grib1
src/pygrib.egg-info/PKG-INFO
src/pygrib.egg-info/SOURCES.txt
src/pygrib.egg-info/dependency_links.txt
src/pygrib.egg-info/requires.txt
src/pygrib.egg-info/top_level.txt
