Metadata-Version: 2.4
Name: pygrib
Version: 2.1.7
Summary: Python module for reading/writing GRIB files
Author-email: Jeff Whitaker <whitaker.jeffrey@gmail.com>
License-Expression: MIT AND (Apache-2.0 OR BSD-2-Clause)
Project-URL: Documentation, https://jswhit.github.io/pygrib/
Project-URL: Repository, https://github.com/jswhit/pygrib
Classifier: Development Status :: 4 - Beta
Classifier: Programming Language :: Python :: 3
Classifier: Programming Language :: Python :: 3.10
Classifier: Programming Language :: Python :: 3.11
Classifier: Programming Language :: Python :: 3.12
Classifier: Programming Language :: Python :: 3.13
Classifier: Programming Language :: Python :: 3.14
Classifier: Intended Audience :: Science/Research
Classifier: Topic :: Software Development :: Libraries :: Python Modules
Requires-Python: >=3.10
License-File: LICENSE
Requires-Dist: packaging
Requires-Dist: pyproj
Requires-Dist: numpy
Dynamic: license-file
